{"blocks":"3,178,534","blockLastSend":"8/16/2024, 2:46:10 PM","blockReward":6,"feeReward":0.08798088,"averageblockfees":0.07653839,"totalSupply":"77,035,546","circulatingSupply":"77,035,546","circulatingSupplyPercentage":"92.21","marketCap":"97,835,144","maxSupply":"83,540,184","fullyDilutedMarketCap":"106,096,034","stakingAmount":100,"stakingPercentage":"36.18","stakingRewardsArray":[{"label":"Daily","rewards":0.0155,"dollars":0.02},{"label":"Monthly","rewards":0.4715,"dollars":0.6},{"label":"Yearly","rewards":5.6575,"dollars":7.18}],"stakingSupply":"27,871,095","stakingValue":"35,396,291","stakingAPY":"5.66","vrscMiningHash":1,"miningRewardsArray":[{"label":"Daily","rewards":0.0051,"dollars":0.01},{"label":"Monthly","rewards":0.1557,"dollars":0.2},{"label":"Yearly","rewards":1.8681,"dollars":2.37}],"vrscNetworkHash":"844.075","vrscOnline":true,"vrscStatusMessage":"Verus Node Running","getAddressBalanceArray":[],"getAddress":"","bitcoinPrice":"57,605.51","ethereumBridgePrice":2583.11,"vrscBridgePrice":1.27,"mkrBridgePrice":1949.53,"vrscBridgeVolumeInDollars24Hours":"455,202","vrscBridgeVolumeInDollars24HoursArray":[{"volume":"28K","barPCT":13},{"volume":"66K","barPCT":30},{"volume":"16K","barPCT":8},{"volume":"20K","barPCT":10},{"volume":"8K","barPCT":4},{"volume":"28K","barPCT":13},{"volume":"6K","barPCT":3},{"volume":"550","barPCT":0},{"volume":"6K","barPCT":3},{"volume":"21K","barPCT":10},{"volume":"218K","barPCT":100},{"volume":"8K","barPCT":4},{"volume":"11","barPCT":0},{"volume":"431","barPCT":0},{"volume":"23K","barPCT":11}],"vrscBridgeVolumeInDollars24HoursArrayYAxis":[{"value":"218K"},{"value":"109K"},{"value":0}],"vrscBridgeVolumeInDollars7Days":"2,265,034","vrscBridgeVolumeInDollars7DaysArray":[{"volume":"676K","barPCT":100},{"volume":"160K","barPCT":24},{"volume":"594K","barPCT":88},{"volume":"376K","barPCT":56},{"volume":"457K","barPCT":68}],"vrscBridgeVolumeInDollars7DaysArrayYAxis":[{"value":"676K"},{"value":"338K"},{"value":0}],"vrscBridgeVolumeInDollars30Days":"14,125,595","vrscBridgeVolumeInDollars30DaysArray":[{"volume":"600K","barPCT":52},{"volume":"604K","barPCT":52},{"volume":"272K","barPCT":23},{"volume":"217K","barPCT":19},{"volume":"375K","barPCT":32},{"volume":"571K","barPCT":49},{"volume":"556K","barPCT":48},{"volume":"593K","barPCT":51},{"volume":"733K","barPCT":63},{"volume":"388K","barPCT":34},{"volume":"320K","barPCT":28},{"volume":"197K","barPCT":17},{"volume":"416K","barPCT":36},{"volume":"470K","barPCT":41},{"volume":"317K","barPCT":27},{"volume":"636K","barPCT":55},{"volume":"387K","barPCT":33},{"volume":"391K","barPCT":34},{"volume":"859K","barPCT":74},{"volume":"1.1M","barPCT":100},{"volume":"505K","barPCT":44},{"volume":"593K","barPCT":51},{"volume":"690K","barPCT":60},{"volume":"676K","barPCT":58},{"volume":"160K","barPCT":14},{"volume":"594K","barPCT":51},{"volume":"376K","barPCT":32},{"volume":"457K","barPCT":39}],"vrscBridgeVolumeInDollars30DaysArrayYAxis":[{"value":"1.1M"},{"value":"579K"},{"value":0}],"estimatedBridgeValueUSD":"9.71","estimatedBridgeValueVRSC":"7.646","currencyBridgeArray":[{"reserves":"2,472,989.9085","priceinreserve":7.65197079,"price":1.27,"origin":"Bridge.vETH","network":"vrsc","coingeckoprice":1.2,"currencyId":"i5w5MuNik5NtLcYmNzcvaoixooEebB6MGV","currencyName":"VRSC"},{"coingeckoprice":1,"reserves":"3,138,318.1901","priceinreserve":9.71064178,"price":1,"origin":"Bridge.vETH","network":"vrsc","currencyId":"iGBs4DWztRNvNEJBt4mqHszLxfKTNHTkhM","currencyName":"DAI.vETH"},{"coingeckoprice":1935.82,"reserves":"1,609.7798","priceinreserve":0.00498101,"price":1949.53,"origin":"Bridge.vETH","network":"vrsc","currencyId":"iCkKJuJScy4Z6NSDK7Mt42ZAB2NEnAE1o4","currencyName":"MKR.vETH"},{"coingeckoprice":2566.45,"reserves":"1,214.9366","priceinreserve":0.00375927,"price":2583.11,"origin":"Bridge.vETH","network":"vrsc","currencyId":"i9nwxtKuVYX4MSbeULLiK2ttVi6rUEhh4X","currencyName":"vETH"}],"estimatedBridgeReserveValue":"12,553,273","kaijuVolumeInDollars24Hours":"1,328","kaijuVolumeInDollars24HoursArray":[{"volume":"27","barPCT":6},{"volume":"475","barPCT":100},{"volume":"124","barPCT":26},{"volume":"254","barPCT":53},{"volume":"26","barPCT":5},{"volume":"141","barPCT":30},{"volume":"128","barPCT":27},{"volume":"51","barPCT":11},{"volume":"103","barPCT":22}],"kaijuVolumeInDollars24HoursArrayYAxis":[{"value":"475"},{"value":"237"},{"value":0}],"kaijuVolumeInDollars7Days":"9,366","kaijuVolumeInDollars7DaysArray":[{"volume":"2K","barPCT":58},{"volume":"796","barPCT":21},{"volume":"3K","barPCT":100},{"volume":"1K","barPCT":38},{"volume":"1K","barPCT":36}],"kaijuVolumeInDollars7DaysArrayYAxis":[{"value":"3K"},{"value":"1K"},{"value":0}],"kaijuVolumeInDollars30Days":"69,303","kaijuVolumeInDollars30DaysArray":[{"volume":"1K","barPCT":24},{"volume":"3K","barPCT":65},{"volume":"2K","barPCT":48},{"volume":"693","barPCT":12},{"volume":"1K","barPCT":29},{"volume":"1K","barPCT":33},{"volume":"2K","barPCT":39},{"volume":"3K","barPCT":53},{"volume":"3K","barPCT":63},{"volume":"1K","barPCT":24},{"volume":"2K","barPCT":43},{"volume":"1K","barPCT":19},{"volume":"1K","barPCT":26},{"volume":"2K","barPCT":36},{"volume":"1K","barPCT":22},{"volume":"1K","barPCT":31},{"volume":"5K","barPCT":100},{"volume":"982","barPCT":17},{"volume":"4K","barPCT":85},{"volume":"5K","barPCT":87},{"volume":"2K","barPCT":42},{"volume":"4K","barPCT":80},{"volume":"2K","barPCT":45},{"volume":"2K","barPCT":36},{"volume":"796","barPCT":14},{"volume":"3K","barPCT":63},{"volume":"1K","barPCT":24},{"volume":"1K","barPCT":23}],"kaijuVolumeInDollars30DaysArrayYAxis":[{"value":"5K"},{"value":"2K"},{"value":0}],"estimatedKaijuValueUSD":"1","estimatedKaijuValueVRSC":"0.783","currencyKaijuArray":[{"reserves":"17,167.5788","priceinreserve":0.78250658,"price":1.28,"origin":"Kaiju","network":"vrsc","coingeckoprice":1.2,"currencyId":"i5w5MuNik5NtLcYmNzcvaoixooEebB6MGV","currencyName":"VRSC"},{"coingeckoprice":1,"reserves":"21,989.1032","priceinreserve":1.002274,"price":1,"origin":"Kaiju","network":"vrsc","currencyId":"i9oCSqKALwJtcv49xUKS2U2i79h1kX6NEY","currencyName":"vUSDT.vETH"},{"coingeckoprice":2566.45,"reserves":"8.4168","priceinreserve":0.00038364,"price":2612.52,"origin":"Kaiju","network":"vrsc","currencyId":"i9nwxtKuVYX4MSbeULLiK2ttVi6rUEhh4X","currencyName":"vETH"},{"coingeckoprice":57605.51,"reserves":"0.3665","priceinreserve":0.0000167,"price":59993.41,"origin":"Kaiju","network":"vrsc","currencyId":"iS8TfRPfVpKo5FVfSUzfHBQxo9KuzpnqLU","currencyName":"tBTC.vETH"}],"estimatedKaijuReserveValue":"87,956","currencyVolumePure24Hours":"16,595","currencyVolumePure24HoursArray":[{"volume":"918","barPCT":16},{"volume":"4K","barPCT":84},{"volume":"180","barPCT":3},{"volume":"233","barPCT":4},{"volume":"40","barPCT":1},{"volume":"5K","barPCT":100},{"volume":"40","barPCT":1},{"volume":"950","barPCT":17},{"volume":"3K","barPCT":69},{"volume":"1","barPCT":0}],"currencyVolumePure24HoursArrayYAxis":[{"value":"5K"},{"value":"2K"},{"value":0}],"currencyVolumePure7Days":"78,569","currencyVolumePure7DaysArray":[{"volume":"16K","barPCT":88},{"volume":"9K","barPCT":54},{"volume":"17K","barPCT":97},{"volume":"18K","barPCT":100},{"volume":"16K","barPCT":91}],"currencyVolumePure7DaysArrayYAxis":[{"value":"18K"},{"value":"9K"},{"value":0}],"currencyVolumePure30Days":"586,121","currencyVolumePure30DaysArray":[{"volume":"10K","barPCT":24},{"volume":"38K","barPCT":88},{"volume":"23K","barPCT":53},{"volume":"10K","barPCT":25},{"volume":"15K","barPCT":36},{"volume":"15K","barPCT":37},{"volume":"19K","barPCT":46},{"volume":"13K","barPCT":31},{"volume":"18K","barPCT":42},{"volume":"14K","barPCT":32},{"volume":"12K","barPCT":29},{"volume":"5K","barPCT":14},{"volume":"28K","barPCT":65},{"volume":"22K","barPCT":52},{"volume":"27K","barPCT":64},{"volume":"23K","barPCT":54},{"volume":"30K","barPCT":70},{"volume":"15K","barPCT":35},{"volume":"43K","barPCT":100},{"volume":"35K","barPCT":83},{"volume":"31K","barPCT":74},{"volume":"34K","barPCT":79},{"volume":"16K","barPCT":37},{"volume":"16K","barPCT":37},{"volume":"9K","barPCT":23},{"volume":"17K","barPCT":41},{"volume":"18K","barPCT":42},{"volume":"16K","barPCT":38}],"currencyVolumePure30DaysArrayYAxis":[{"value":"43K"},{"value":"21K"},{"value":0}],"currencyPureArray":[{"reserves":"503,558.5981","priceinreserve":4.31638625,"origin":"Pure","network":"vrsc","priceNative":0.00002141,"pricelabel":"tBTCvETH","price":1.23,"coingeckoprice":1.27,"coingeckoLabel":"Bridge.vETH","currencyId":"i5w5MuNik5NtLcYmNzcvaoixooEebB6MGV","currencyName":"VRSC"},{"coingeckoprice":57605.51,"coingeckoLabel":"Coingecko","reserves":"10.7793","priceinreserve":0.00009239,"origin":"Pure","network":"vrsc","priceNative":46715.52,"pricelabel":"VRSC","price":59328.71,"currencyId":"iS8TfRPfVpKo5FVfSUzfHBQxo9KuzpnqLU","currencyName":"tBTC.vETH"}],"estimatedPureValueUSD":"5.48","estimatedPureValueVRSC":"4.316","estimatedPureReserveValueUSDBTC":"1,241,889","estimatedPureReserveValueUSDVRSC":"1,279,039","currencyVolumeSwitch24Hours":"88","currencyVolumeSwitch24HoursArray":[{"volume":"34","barPCT":62},{"volume":"55","barPCT":100}],"currencyVolumeSwitch24HoursArrayYAxis":[{"value":"55"},{"value":"27"},{"value":0}],"currencyVolumeSwitch7Days":"454","currencyVolumeSwitch7DaysArray":[{"volume":"207","barPCT":100},{"volume":"26","barPCT":13},{"volume":"104","barPCT":50},{"volume":"28","barPCT":14},{"volume":"88","barPCT":43}],"currencyVolumeSwitch7DaysArrayYAxis":[{"value":"207"},{"value":"103"},{"value":0}],"currencyVolumeSwitch30Days":"2,701","currencyVolumeSwitch30DaysArray":[{"volume":"41","barPCT":7},{"volume":"47","barPCT":8},{"volume":"28","barPCT":5},{"volume":"6","barPCT":1},{"volume":"92","barPCT":17},{"volume":"19","barPCT":3},{"volume":"33","barPCT":6},{"volume":"98","barPCT":18},{"volume":"68","barPCT":12},{"volume":"3","barPCT":1},{"volume":"27","barPCT":5},{"volume":"0","barPCT":0},{"volume":"14","barPCT":3},{"volume":"39","barPCT":7},{"volume":"16","barPCT":3},{"volume":"122","barPCT":22},{"volume":"126","barPCT":23},{"volume":"70","barPCT":13},{"volume":"366","barPCT":66},{"volume":"293","barPCT":53},{"volume":"24","barPCT":4},{"volume":"162","barPCT":29},{"volume":"553","barPCT":100},{"volume":"207","barPCT":37},{"volume":"26","barPCT":5},{"volume":"104","barPCT":19},{"volume":"28","barPCT":5},{"volume":"88","barPCT":16}],"currencyVolumeSwitch30DaysArrayYAxis":[{"value":"553"},{"value":"276"},{"value":0}],"currencySwitchArray":[{"reserves":"1,704.6450","priceinreserve":0.97164891,"origin":"Switch","network":"vrsc","price":1.28,"coingeckoprice":1.27,"coingeckoLabel":"Bridge.vETH","currencyId":"i5w5MuNik5NtLcYmNzcvaoixooEebB6MGV","currencyName":"VRSC"},{"reserves":"2,870.0902","priceinreserve":1.24644076,"origin":"Switch","network":"vrsc","price":1,"coingeckoprice":1,"coingeckoLabel":"Coingecko","currencyId":"iGBs4DWztRNvNEJBt4mqHszLxfKTNHTkhM","currencyName":"DAI.vETH"},{"reserves":"2,867.9161","priceinreserve":1.24549657,"origin":"Switch","network":"vrsc","price":1,"coingeckoprice":1,"coingeckoLabel":"Coingecko","currencyId":"i61cV2uicKSi1rSMQCBNQeSYC3UAi9GVzd","currencyName":"vUSDC.vETH"},{"reserves":"5,344.7273","priceinreserve":1.16057085,"origin":"Switch","network":"vrsc","price":1.07,"coingeckoprice":1.09,"coingeckoLabel":"Coingecko","currencyId":"iC5TQFrFXSYLQGkiZ8FYmZHFJzaRF5CYgE","currencyName":"EURC.vETH"}],"estimatedSwitchValue":"1.25","estimatedSwitchReserveValue":"13,667","estimatedSwitchValueUSDVRSC":"0.984","currencyVolumeNati24Hours":"16,843","currencyVolumeNati24HoursArray":[{"volume":"4K","barPCT":84},{"volume":"100","barPCT":2},{"volume":"3K","barPCT":52},{"volume":"10","barPCT":0},{"volume":"2K","barPCT":46},{"volume":"5K","barPCT":100},{"volume":"2","barPCT":0}],"currencyVolumeNati24HoursArrayYAxis":[{"value":"5K"},{"value":"2K"},{"value":0}],"currencyVolumeNati7Days":"35,857","currencyVolumeNati7DaysArray":[{"volume":"19K","barPCT":100},{"volume":"16K","barPCT":89}],"currencyVolumeNati7DaysArrayYAxis":[{"value":"19K"},{"value":"9K"},{"value":0}],"currencyVolumeNati30Days":"35,857","currencyVolumeNati30DaysArray":[{"volume":"19K","barPCT":100},{"volume":"16K","barPCT":89}],"currencyVolumeNati30DaysArrayYAxis":[{"value":"19K"},{"value":"9K"},{"value":0}],"currencyNatiArray":[{"reserves":"1,240,413.4011","priceinreserve":27.99165024,"origin":"NATI","network":"vrsc","priceNative":253.795,"pricelabel":"NATI.vETH","price":1.29,"coingeckoprice":1.27,"coingeckoLabel":"Bridge.vETH","currencyId":"i5w5MuNik5NtLcYmNzcvaoixooEebB6MGV","currencyName":"VRSC"},{"coingeckoprice":"0.00000051","coingeckoLabel":"Coingecko","reserves":"314,811,294.4669","priceinreserve":7104.15385835,"origin":"NATI","network":"vrsc","priceNative":"0.00394","pricelabel":"VRSC","price":"0.00500","currencyId":"iL62spNN42Vqdxh8H5nrfNe8d6Amsnfkdx","currencyName":"NATI.vETH"}],"estimatedNatiValueUSD":"35.55","estimatedNatiValueVRSC":"27.992","estimatedNatiReserveValueUSDNATI":"3,211,075","estimatedNatiReserveValueUSDVRSC":"3,150,650","varrrOnline":true,"getVarrrAddressBalanceArray":[],"getVarrrAddress":"","varrrblocks":"189,398","varrrblockLastSend":"8/16/2024, 2:46:42 PM","varrrblockReward":0.08,"varrrfeeReward":0.00065529,"varrraverageblockfees":0.00112874,"varrrStakingAmount":100,"varrrStakingRewardsArray":[{"label":"Daily","rewards":0.0212,"dollars":0},{"label":"Monthly","rewards":0.644,"dollars":0.12},{"label":"Yearly","rewards":7.7282,"dollars":1.39}],"varrrStakingSupply":"272,044","varrrStakingAPY":"7.73","varrrMiningHash":1,"varrrMiningRewardsArray":[{"label":"Daily","rewards":0.0002,"dollars":0},{"label":"Monthly","rewards":0.0046,"dollars":0},{"label":"Yearly","rewards":0.055,"dollars":0.01}],"varrrNetworkHash":"382.439","varrrBridgeVolumeInDollars24Hours":"5,137","varrrBridgeVolumeInDollars24HoursArray":[{"volume":"321","barPCT":24},{"volume":"841","barPCT":62},{"volume":"320","barPCT":24},{"volume":"1K","barPCT":100},{"volume":"1K","barPCT":94},{"volume":"422","barPCT":31},{"volume":"611","barPCT":45}],"varrrBridgeVolumeInDollars24HoursArrayYAxis":[{"value":"1K"},{"value":"677"},{"value":0}],"varrrBridgeVolumeInDollars7Days":"14,246","varrrBridgeVolumeInDollars7DaysArray":[{"volume":"4K","barPCT":90},{"volume":"1K","barPCT":38},{"volume":"1K","barPCT":36},{"volume":"258","barPCT":5},{"volume":"4","barPCT":0},{"volume":"421","barPCT":8},{"volume":"5K","barPCT":100}],"varrrBridgeVolumeInDollars7DaysArrayYAxis":[{"value":"5K"},{"value":"2K"},{"value":0}],"varrrBridgeVolumeInDollars30Days":"47,134","varrrBridgeVolumeInDollars30DaysArray":[{"volume":"429","barPCT":8},{"volume":"940","barPCT":18},{"volume":"21","barPCT":0},{"volume":"310","barPCT":6},{"volume":"700","barPCT":14},{"volume":"1K","barPCT":37},{"volume":"1K","barPCT":32},{"volume":"1K","barPCT":22},{"volume":"1K","barPCT":27},{"volume":"1K","barPCT":30},{"volume":"3K","barPCT":61},{"volume":"825","barPCT":16},{"volume":"837","barPCT":16},{"volume":"1K","barPCT":24},{"volume":"826","barPCT":16},{"volume":"1K","barPCT":27},{"volume":"771","barPCT":15},{"volume":"752","barPCT":15},{"volume":"3K","barPCT":59},{"volume":"4K","barPCT":87},{"volume":"1K","barPCT":32},{"volume":"1K","barPCT":32},{"volume":"2K","barPCT":45},{"volume":"4K","barPCT":90},{"volume":"1K","barPCT":38},{"volume":"1K","barPCT":36},{"volume":"258","barPCT":5},{"volume":"4","barPCT":0},{"volume":"421","barPCT":8},{"volume":"5K","barPCT":100}],"varrrBridgeVolumeInDollars30DaysArrayYAxis":[{"value":"5K"},{"value":"2K"},{"value":0}],"currencyVarrrBridgeArray":[{"reserves":"44,629.9307","priceinreserve":2.42748889,"origin":"Bridge.vARRR","network":"vARRR","priceNative":0.00002108,"pricelabel":"tBTCvETH","price":1.21,"coingeckoprice":1.27,"coingeckoLabel":"Bridge.vETH","currencyId":"i5w5MuNik5NtLcYmNzcvaoixooEebB6MGV","currencyName":"VRSC"},{"coingeckoprice":0.17,"coingeckoLabel":"Coingecko","reserves":"318,202.9909","priceinreserve":17.30753812,"origin":"Bridge.vARRR","network":"vARRR","priceNative":0.14,"pricelabel":"VRSC","price":0.18,"currencyId":"iExBJfZYK7KREDpuhj6PzZBzqMAKaFg7d2","currencyName":"vARRR"},{"reserves":"5,736.2699","priceinreserve":0.31200432,"origin":"Bridge.vARRR","network":"vARRR","priceNative":7.78,"pricelabel":"VRSC","price":9.88,"coingeckoprice":"9.71","coingeckoLabel":"Bridge.vETH","currencyId":"i3f7tSctFkiPpiedY8QR5Tep9p4qDVebDx","currencyName":"Bridge.vETH"},{"coingeckoprice":57605.51,"coingeckoLabel":"Coingecko","reserves":"0.9406","priceinreserve":0.00005116,"origin":"Bridge.vARRR","network":"vARRR","priceNative":47448.4,"pricelabel":"VRSC","price":60259.47,"currencyId":"iS8TfRPfVpKo5FVfSUzfHBQxo9KuzpnqLU","currencyName":"tBTC.vETH"}],"estimatedVarrrBridgeValueUSD":"3.08","estimatedVarrrBridgeValueVRSC":"2.427","estimatedVarrrBridgeReserveValueUSDBTC":"216,735","estimatedVarrrBridgeReserveValueUSDVRSC":"226,720","vdexOnline":false,"vdexStatusMessage":"Updating and syncing vDEX PBaaS...","btcPriceArray":[{"coingeckoprice":57605.51,"coingeckoLabel":"Coingecko","reserves":"0.9406","priceinreserve":0.00005116,"origin":"Bridge.vARRR","network":"vARRR","priceNative":47448.4,"pricelabel":"VRSC","price":60259.47,"currencyId":"iS8TfRPfVpKo5FVfSUzfHBQxo9KuzpnqLU","currencyName":"tBTC.vETH"},{"coingeckoprice":57605.51,"reserves":"0.3665","priceinreserve":0.0000167,"price":59993.41,"origin":"Kaiju","network":"vrsc","currencyId":"iS8TfRPfVpKo5FVfSUzfHBQxo9KuzpnqLU","currencyName":"tBTC.vETH"},{"coingeckoprice":57605.51,"coingeckoLabel":"Coingecko","reserves":"10.7793","priceinreserve":0.00009239,"origin":"Pure","network":"vrsc","priceNative":46715.52,"pricelabel":"VRSC","price":59328.71,"currencyId":"iS8TfRPfVpKo5FVfSUzfHBQxo9KuzpnqLU","currencyName":"tBTC.vETH"},{"currencyId":"iS8TfRPfVpKo5FVfSUzfHBQxo9KuzpnqLU","price":57605.51,"name":"bitcoin","origin":"Coingecko","network":"btc"}],"ethereumPriceArray":[{"coingeckoprice":2566.45,"reserves":"8.4168","priceinreserve":0.00038364,"price":2612.52,"origin":"Kaiju","network":"vrsc","currencyId":"i9nwxtKuVYX4MSbeULLiK2ttVi6rUEhh4X","currencyName":"vETH"},{"coingeckoprice":2566.45,"reserves":"1,214.9366","priceinreserve":0.00375927,"price":2583.11,"origin":"Bridge.vETH","network":"vrsc","currencyId":"i9nwxtKuVYX4MSbeULLiK2ttVi6rUEhh4X","currencyName":"vETH"},{"currencyId":"i9nwxtKuVYX4MSbeULLiK2ttVi6rUEhh4X","price":2566.45,"name":"ethereum","origin":"Coingecko","network":"ethereum"}],"makerPriceArray":[{"coingeckoprice":1935.82,"reserves":"1,609.7798","priceinreserve":0.00498101,"price":1949.53,"origin":"Bridge.vETH","network":"vrsc","currencyId":"iCkKJuJScy4Z6NSDK7Mt42ZAB2NEnAE1o4","currencyName":"MKR.vETH"},{"currencyId":"iCkKJuJScy4Z6NSDK7Mt42ZAB2NEnAE1o4","price":1935.82,"name":"maker","origin":"Coingecko","network":"ethereum"}],"vrscPriceArray":[{"reserves":"1,240,413.4011","priceinreserve":27.99165024,"origin":"NATI","network":"vrsc","priceNative":253.795,"pricelabel":"NATI.vETH","price":1.29,"coingeckoprice":1.27,"coingeckoLabel":"Bridge.vETH","currencyId":"i5w5MuNik5NtLcYmNzcvaoixooEebB6MGV","currencyName":"VRSC"},{"reserves":"17,167.5788","priceinreserve":0.78250658,"price":1.28,"origin":"Kaiju","network":"vrsc","coingeckoprice":1.2,"currencyId":"i5w5MuNik5NtLcYmNzcvaoixooEebB6MGV","currencyName":"VRSC"},{"reserves":"1,704.6450","priceinreserve":0.97164891,"origin":"Switch","network":"vrsc","price":1.28,"coingeckoprice":1.27,"coingeckoLabel":"Bridge.vETH","currencyId":"i5w5MuNik5NtLcYmNzcvaoixooEebB6MGV","currencyName":"VRSC"},{"reserves":"2,472,989.9085","priceinreserve":7.65197079,"price":1.27,"origin":"Bridge.vETH","network":"vrsc","coingeckoprice":1.2,"currencyId":"i5w5MuNik5NtLcYmNzcvaoixooEebB6MGV","currencyName":"VRSC"},{"reserves":"503,558.5981","priceinreserve":4.31638625,"origin":"Pure","network":"vrsc","priceNative":0.00002141,"pricelabel":"tBTCvETH","price":1.23,"coingeckoprice":1.27,"coingeckoLabel":"Bridge.vETH","currencyId":"i5w5MuNik5NtLcYmNzcvaoixooEebB6MGV","currencyName":"VRSC"},{"reserves":"44,629.9307","priceinreserve":2.42748889,"origin":"Bridge.vARRR","network":"vARRR","priceNative":0.00002108,"pricelabel":"tBTCvETH","price":1.21,"coingeckoprice":1.27,"coingeckoLabel":"Bridge.vETH","currencyId":"i5w5MuNik5NtLcYmNzcvaoixooEebB6MGV","currencyName":"VRSC"},{"currencyId":"i5w5MuNik5NtLcYmNzcvaoixooEebB6MGV","price":1.2,"name":"verus-coin","origin":"Coingecko","network":"vrsc"}],"arrrPriceArray":[{"coingeckoprice":0.17,"coingeckoLabel":"Coingecko","reserves":"318,202.9909","priceinreserve":17.30753812,"origin":"Bridge.vARRR","network":"vARRR","priceNative":0.14,"pricelabel":"VRSC","price":0.18,"currencyId":"iExBJfZYK7KREDpuhj6PzZBzqMAKaFg7d2","currencyName":"vARRR"},{"currencyId":"iExBJfZYK7KREDpuhj6PzZBzqMAKaFg7d2","price":0.17,"name":"pirate-chain","origin":"Coingecko","network":"piratechain"}],"vrscReserveArray":[{"basket":"Bridge.vETH","reserve":"12,553,273","via":""},{"basket":"NATI","reserve":"3,150,650","via":"via VRSC"},{"basket":"Pure","reserve":"1,279,039","via":"via VRSC"},{"basket":"Bridge.vARRR","reserve":"226,720","via":"via VRSC"},{"basket":"Kaiju","reserve":"87,956","via":""},{"basket":"Switch","reserve":"13,667","via":""}],"threeFoldNodeArray":[],"threefoldNodeString":"","_locals":{}}